[
  {
    "id": 1,
    "pwd": "1234569",
    "userName": "123456799",
    "age": 18,
    "regTime": "19-3-15 下午1:05",
    "birthday": "18-12-9 下午4:00",
    "description": "1235655559",
    "tel": "18322693235",
    "email": "790872612@qq.com",
    "sex": true
  },
  {
    "id": 2,
    "pwd": "1234569",
    "userName": "123456799",
    "age": 18,
    "regTime": "19-3-15 下午1:14",
    "birthday": "18-12-9 下午4:00",
    "description": "1235655559",
    "tel": "18322693235",
    "email": "790872612@qq.com",
    "sex": true
  },
  {
    "id": 3,
    "pwd": "1234569",
    "userName": "乔风鳞",
    "age": 18,
    "regTime": "19-3-15 下午3:40",
    "birthday": "18-12-9 下午4:00",
    "description": "1235655559",
    "tel": "18322693235",
    "email": "790872612@qq.com",
    "sex": true
  },
  {
    "id": 4,
    "pwd": "1234569",
    "userName": "乔风鳞1",
    "age": 18,
    "regTime": "19-3-17 下午3:18",
    "birthday": "18-12-9 下午4:00",
    "description": "1235655559",
    "tel": "18322693235",
    "email": "790872612@qq.com",
    "sex": true
  },
  {
    "id": 5,
    "pwd": "1234569",
    "userName": "18322693235",
    "age": 18,
    "regTime": "19-4-29 下午1:03",
    "birthday": "18-12-9 下午4:00",
    "description": "1235655559",
    "tel": "18322693237",
    "email": "790872612@qq.com",
    "sex": false
  }
]